simplesqs/__init__.py
simplesqs/message.py
simplesqs-0.4.0.dist-info/LICENSE.txt
simplesqs-0.4.0.dist-info/METADATA
simplesqs-0.4.0.dist-info/WHEEL
simplesqs-0.4.0.dist-info/top_level.txt
simplesqs-0.4.0.dist-info/RECORD
